recursive_itertools/__init__.py
recursive_itertools-0.2.2.data/data/LICENSE
recursive_itertools-0.2.2.data/data/README.md
recursive_itertools-0.2.2.data/data/VERSION
recursive_itertools-0.2.2.dist-info/DESCRIPTION.rst
recursive_itertools-0.2.2.dist-info/METADATA
recursive_itertools-0.2.2.dist-info/RECORD
recursive_itertools-0.2.2.dist-info/WHEEL
recursive_itertools-0.2.2.dist-info/metadata.json
recursive_itertools-0.2.2.dist-info/top_level.txt
