Metadata-Version: 2.0
Name: recursive-itertools
Version: 0.2.2
Summary:   Iteration tools for recursive structures.
Home-page: https://github.com/mmontagna/recursive-itertools
Author: Marco Montagna
Author-email: marcojoemontagna@gmail.com
License: Copyright (c) 2018 Marco Montagna
